orthanc_ext/__init__.py
orthanc_ext/event_dispatcher.py
orthanc_ext/logging_configurator.py
orthanc_ext/orthanc.py
orthanc_ext/orthanc_utilities.py
orthanc_ext/python_utilities.py
orthanc_ext/requests_utilities.py
orthanc_ext/scripts/__init__.py
orthanc_ext/scripts/auto_forward.py
orthanc_ext/scripts/auto_retries.py
orthanc_server_extensions-3.1.9.dist-info/LICENSE
orthanc_server_extensions-3.1.9.dist-info/METADATA
orthanc_server_extensions-3.1.9.dist-info/WHEEL
orthanc_server_extensions-3.1.9.dist-info/top_level.txt
orthanc_server_extensions-3.1.9.dist-info/RECORD
