Metadata-Version: 2.1
Name: orthanc-server-extensions
Version: 3.1.9
Summary: A simple Orthanc python plugin based framework to extend Orthanc's feature set with testable python scripts.
Home-page: https://github.com/walkIT-nl/orthanc-server-extensions
Author: WalkIT
Author-email: code@walkit.nl
License: GNU Affero General Public License v3
Keywords: orthanc testing
Platform: UNKNOWN
Classifier: Development Status :: 2 - Pre-Alpha
Classifier: Intended Audience :: Developers
Classifier: License :: OSI Approved :: GNU Affero General Public License v3
Classifier: Natural Language :: English
Classifier: Programming Language :: Python :: 3
Classifier: Programming Language :: Python :: 3.7
Classifier: Programming Language :: Python :: 3.8
Classifier: Programming Language :: Python :: 3.9
Requires-Python: >=3.7
Requires-Dist: requests
Requires-Dist: requests-toolbelt
Requires-Dist: dataclasses
